<?xml version="1.0" encoding="UTF-8"?>
<objects serializationModel="Studio.02.02.00">
	<object class="AudioFile" id="{821136a1-6257-4416-b96c-9428eefc92e4}">
		<property name="assetPath">
			<value>Ambient - Foley/BVKER - Footsteps Forest Ambience 01.wav</value>
		</property>
		<property name="isStreaming">
			<value>true</value>
		</property>
		<property name="frequencyInKHz">
			<value>44.0999985</value>
		</property>
		<property name="channelCount">
			<value>2</value>
		</property>
		<property name="length">
			<value>62.103197278911566</value>
		</property>
		<relationship name="masterAssetFolder">
			<destination>{63dfca91-bb45-40a6-80d2-d53f46e67948}</destination>
		</relationship>
	</object>
</objects>
