<?xml version="1.0" encoding="UTF-8"?>
<objects serializationModel="Studio.02.02.00">
	<object class="AudioFile" id="{af7e9c9c-91e5-4f91-9674-72946a414cc2}">
		<property name="assetPath">
			<value>Dialogs/DIAL_A01_S01_40_HASA.mp3</value>
		</property>
		<property name="frequencyInKHz">
			<value>44.0999985</value>
		</property>
		<property name="channelCount">
			<value>2</value>
		</property>
		<property name="length">
			<value>4.0751020408163265</value>
		</property>
		<relationship name="masterAssetFolder">
			<destination>{63dfca91-bb45-40a6-80d2-d53f46e67948}</destination>
		</relationship>
	</object>
</objects>
